{
  "parent": "strange:core/potions",
  "display": {
    "icon": {
      "item": "strange:cask"
    },
    "title": {
      "translate": "advancements.strange.obtain_cask.title"
    },
    "description": {
      "translate": "advancements.strange.obtain_cask.description"
    },
    "frame": "task",
    "show_toast": false,
    "announce_to_chat": false,
    "hidden": false
  },
  "criteria": {
    "obtained_cask": {
      "trigger": "minecraft:inventory_changed",
      "conditions": {
        "items": [
          {
            "items": ["strange:cask"]
          }
        ]
      }
    }
  },
  "requirements": [
    [
      "obtained_cask"
    ]
  ]
}