{
  "type": "gather",
  "level": 1,
  "professions": [
    "librarian"
  ],
  "gather": [
    {
      "list": "strange:book_ingredients",
      "amount": 10
    }
  ],
  "reward_items": [
    {
      "list": "strange:emerald",
      "amount": 1
    },
    {
      "list": "strange:stone_tools",
      "amount": 1
    },
    {
      "list": "strange:candles",
      "amount": 3
    },
    {
      "list": "strange:overworld_wooden_slabs",
      "amount": 12
    },
    {
      "list": "strange:lecterns",
      "amount": 1
    }
  ]
}