{
  "parent": "strange:find_vaults",
  "display": {
    "icon": {
      "item": "strange:totem_of_flying"
    },
    "title": {
      "translate": "advancements.strange.rare_totem.title"
    },
    "description": {
      "translate": "advancements.strange.rare_totem.description"
    },
    "frame": "task",
    "show_toast": true,
    "announce_to_chat": false,
    "hidden": false,
    "background": "minecraft:textures/gui/advancements/backgrounds/adventure.png"
  },
  "criteria": {
    "find_totem_of_enchanting": {
      "trigger": "minecraft:inventory_changed",
      "conditions": {
        "items": [
          {
            "item": "strange:totem_of_enchanting"
          }
        ]
      }
    },
    "find_totem_of_transferring": {
      "trigger": "minecraft:inventory_changed",
      "conditions": {
        "items": [
          {
            "item": "strange:totem_of_transferring"
          }
        ]
      }
    },
    "find_totem_of_flying": {
      "trigger": "minecraft:inventory_changed",
      "conditions": {
        "items": [
          {
            "item": "strange:totem_of_flying"
          }
        ]
      }
    }
  },
  "requirements": [
    [
      "find_totem_of_preserving",
      "find_totem_of_enchanting",
      "find_totem_of_transferring",
      "find_totem_of_flying"
    ]
  ]
}